{"type":"FeatureCollection","features":[{"id":"6144","type":"Feature","properties":{"FULLNAME":"I- 10","RTTYP":"I"},"geometry":{"type":"LineString","coordinates":[[-82.4575,30.2572],[-82.3325,30.2541],[-82.2899,30.2331],[-82.1715,30.2612],[-82.1154,30.259],[-82.0496,30.2816]]}},{"id":"6145","type":"Feature","properties":{"FULLNAME":"I- 10","RTTYP":"I"},"geometry":{"type":"LineString","coordinates":[[-82.0496,30.2816],[-82.0372,30.2838]]}},{"id":"6146","type":"Feature","properties":{"FULLNAME":"I- 10","RTTYP":"I"},"geometry":{"type":"LineString","coordinates":[[-83.1936,30.3581],[-83.4296,30.4133],[-83.4676,30.4351],[-83.6108,30.4317],[-83.7244,30.4455]]}},{"id":"6170","type":"Feature","properties":{"FULLNAME":"I- 10","RTTYP":"I"},"geometry":{"type":"LineString","coordinates":[[-82.7947,30.2743],[-82.9075,30.2999],[-82.9929,30.3486],[-83.0431,30.3529],[-83.1059,30.3373],[-83.1936,30.3581]]}},{"id":"6171","type":"Feature","properties":{"FULLNAME":"I- 10","RTTYP":"I"},"geometry":{"type":"LineString","coordinates":[[-82.7947,30.2741],[-82.9112,30.3005],[-82.993,30.3484],[-83.0751,30.3489],[-83.1059,30.337],[-83.1936,30.3578]]}},{"id":"6179","type":"Feature","properties":{"FULLNAME":"I- 10","RTTYP":"I"},"geometry":{"type":"LineString","coordinates":[[-82.4575,30.2572],[-82.6412,30.2418],[-82.6927,30.2453],[-82.7947,30.2743]]}},{"id":"6194","type":"Feature","properties":{"FULLNAME":"I- 10","RTTYP":"I"},"geometry":{"type":"LineString","coordinates":[[-81.6803,30.3244],[-81.9216,30.3022],[-81.9612,30.2907],[-82.0372,30.2838]]}},{"id":"6214","type":"Feature","properties":{"FULLNAME":"I- 10","RTTYP":"I"},"geometry":{"type":"LineString","coordinates":[[-84.0412,30.484],[-83.9892,30.4896],[-83.9377,30.4788],[-83.8235,30.4726],[-83.7244,30.4455]]}},{"id":"6220","type":"Feature","properties":{"FULLNAME":"I- 10","RTTYP":"I"},"geometry":{"type":"LineString","coordinates":[[-83.7244,30.4453],[-83.6115,30.4314],[-83.4686,30.435],[-83.4289,30.4126],[-83.1936,30.3578]]}},{"id":"6223","type":"Feature","properties":{"FULLNAME":"I- 10","RTTYP":"I"},"geometry":{"type":"LineString","coordinates":[[-84.0412,30.4837],[-83.9889,30.4894],[-83.9381,30.4786],[-83.8234,30.4723],[-83.7244,30.4453]]}},{"id":"6237","type":"Feature","properties":{"FULLNAME":"I- 10","RTTYP":"I"},"geometry":{"type":"LineString","coordinates":[[-82.4575,30.2567],[-82.3336,30.2538],[-82.2899,30.2328],[-82.1701,30.2611],[-82.1156,30.2587],[-82.0496,30.2814]]}},{"id":"6274","type":"Feature","properties":{"FULLNAME":"I- 10","RTTYP":"I"},"geometry":{"type":"LineString","coordinates":[[-82.7947,30.2741],[-82.6927,30.245],[-82.6427,30.2416],[-82.4575,30.2567]]}},{"id":"6275","type":"Feature","properties":{"FULLNAME":"I- 10","RTTYP":"I"},"geometry":{"type":"LineString","coordinates":[[-82.0496,30.2814],[-82.0375,30.2835]]}},{"id":"6288","type":"Feature","properties":{"FULLNAME":"I- 10","RTTYP":"I"},"geometry":{"type":"LineString","coordinates":[[-81.6798,30.3252],[-82.0375,30.2835]]}},{"id":"9439","type":"Feature","properties":{"FULLNAME":"I- 75","RTTYP":"I"},"geometry":{"type":"LineString","coordinates":[[-83.7042,31.8047],[-83.7464,31.9289],[-83.7624,32.0294]]}},{"id":"9472","type":"Feature","properties":{"FULLNAME":"I- 75","RTTYP":"I"},"geometry":{"type":"LineString","coordinates":[[-82.7946,30.3054],[-82.8329,30.3464]]}},{"id":"9479","type":"Feature","properties":{"FULLNAME":"I- 75","RTTYP":"I"},"geometry":{"type":"LineString","coordinates":[[-83.3979,31.0299],[-83.3603,30.9025],[-83.2944,30.7753],[-83.2427,30.698],[-83.1724,30.6264]]}},{"id":"9484","type":"Feature","properties":{"FULLNAME":"I- 75","RTTYP":"I"},"geometry":{"type":"LineString","coordinates":[[-82.8328,30.3466],[-82.9166,30.4388],[-82.9839,30.4796],[-83.0394,30.498],[-83.1302,30.6051],[-83.1724,30.6264]]}},{"id":"9493","type":"Feature","properties":{"FULLNAME":"I- 75","RTTYP":"I"},"geometry":{"type":"LineString","coordinates":[[-83.4817,31.3267],[-83.5065,31.4203],[-83.5306,31.4479],[-83.529,31.4675],[-83.5158,31.4844],[-83.5152,31.5141],[-83.56,31.5962]]}},{"id":"9499","type":"Feature","properties":{"FULLNAME":"I- 75","RTTYP":"I"},"geometry":{"type":"LineString","coordinates":[[-83.482,31.3267],[-83.5064,31.4197],[-83.5307,31.4479],[-83.5292,31.4676],[-83.516,31.4845],[-83.5155,31.5146],[-83.5602,31.5962]]}},{"id":"9507","type":"Feature","properties":{"FULLNAME":"I- 75","RTTYP":"I"},"geometry":{"type":"LineString","coordinates":[[-82.8329,30.3464],[-82.9169,30.4384],[-82.9837,30.4791],[-83.0387,30.4971],[-83.1286,30.6031],[-83.1729,30.6264]]}},{"id":"9553","type":"Feature","properties":{"FULLNAME":"I- 75","RTTYP":"I"},"geometry":{"type":"LineString","coordinates":[[-82.7946,30.3054],[-82.7606,30.277],[-82.7383,30.2393],[-82.7072,30.2159],[-82.6317,30.0754],[-82.6032,30.004],[-82.5828,29.9885],[-82.5588,29.9265]]}},{"id":"9563","type":"Feature","properties":{"FULLNAME":"I- 75","RTTYP":"I"},"geometry":{"type":"LineString","coordinates":[[-83.3982,31.0299],[-83.3605,30.9024],[-83.2947,30.7752],[-83.2431,30.6979],[-83.1729,30.6264]]}},{"id":"9572","type":"Feature","properties":{"FULLNAME":"I- 75","RTTYP":"I"},"geometry":{"type":"LineString","coordinates":[[-82.5586,29.9266],[-82.5831,29.9899],[-82.6031,30.0042],[-82.6317,30.0761],[-82.7072,30.2163],[-82.7384,30.2401],[-82.7612,30.2782],[-82.7946,30.3059]]}},{"id":"9580","type":"Feature","properties":{"FULLNAME":"I- 75","RTTYP":"I"},"geometry":{"type":"LineString","coordinates":[[-83.5602,31.5962],[-83.7045,31.8047]]}},{"id":"9581","type":"Feature","properties":{"FULLNAME":"I- 75","RTTYP":"I"},"geometry":{"type":"LineString","coordinates":[[-83.7045,31.8047],[-83.7467,31.9287],[-83.7627,32.0294]]}},{"id":"9582","type":"Feature","properties":{"FULLNAME":"I- 75","RTTYP":"I"},"geometry":{"type":"LineString","coordinates":[[-83.56,31.5962],[-83.7042,31.8047]]}},{"id":"9584","type":"Feature","properties":{"FULLNAME":"I- 75","RTTYP":"I"},"geometry":{"type":"LineString","coordinates":[[-83.3979,31.0299],[-83.3976,31.0572],[-83.4482,31.1616],[-83.4817,31.3267]]}},{"id":"9586","type":"Feature","properties":{"FULLNAME":"I- 75","RTTYP":"I"},"geometry":{"type":"LineString","coordinates":[[-83.3982,31.0299],[-83.3986,31.0587],[-83.4484,31.1612],[-83.482,31.3267]]}},{"id":"9588","type":"Feature","properties":{"FULLNAME":"I- 75","RTTYP":"I"},"geometry":{"type":"LineString","coordinates":[[-82.7946,30.3059],[-82.8328,30.3466]]}},{"id":"16793","type":"Feature","properties":{"FULLNAME":"US Hwy 41","RTTYP":"U"},"geometry":{"type":"LineString","coordinates":[[-83.3556,30.8947],[-83.3879,30.9922]]}},{"id":"16799","type":"Feature","properties":{"FULLNAME":"US Hwy 41","RTTYP":"U"},"geometry":{"type":"LineString","coordinates":[[-83.3882,30.9923],[-83.3558,30.8947]]}}],"crs":{"type":"name","properties":{"name":"urn:ogc:def:crs:EPSG::4269"}}}