{"type":"FeatureCollection","features":[{"id":"1590","type":"Feature","properties":{"FULLNAME":"US Hwy 71","RTTYP":"U"},"geometry":{"type":"LineString","coordinates":[[-92.4694,31.4096],[-92.4372,31.3824]]}},{"id":"1591","type":"Feature","properties":{"FULLNAME":"US Hwy 71","RTTYP":"U"},"geometry":{"type":"LineString","coordinates":[[-92.4374,31.3823],[-92.4709,31.4089]]}},{"id":"5338","type":"Feature","properties":{"FULLNAME":"Claybrook Cottingham Expy","RTTYP":"M"},"geometry":{"type":"LineString","coordinates":[[-92.4419,31.307],[-92.4362,31.3121]]}},{"id":"5339","type":"Feature","properties":{"FULLNAME":"Claybrook Cottingham Expy","RTTYP":"M"},"geometry":{"type":"LineString","coordinates":[[-92.442,31.3072],[-92.4366,31.3125]]}},{"id":"5709","type":"Feature","properties":{"FULLNAME":"US Hwy 167","RTTYP":"U"},"geometry":{"type":"LineString","coordinates":[[-92.0158,30.2594],[-92.0533,30.379]]}},{"id":"5710","type":"Feature","properties":{"FULLNAME":"US Hwy 167","RTTYP":"U"},"geometry":{"type":"LineString","coordinates":[[-92.0155,30.2595],[-92.053,30.379]]}},{"id":"5711","type":"Feature","properties":{"FULLNAME":"US Hwy 167","RTTYP":"U"},"geometry":{"type":"LineString","coordinates":[[-92.429,31.2465],[-92.4467,31.302],[-92.417,31.3299],[-92.4119,31.3527],[-92.4442,31.3915],[-92.4709,31.4089]]}},{"id":"5712","type":"Feature","properties":{"FULLNAME":"US Hwy 167","RTTYP":"U"},"geometry":{"type":"LineString","coordinates":[[-92.4694,31.4096],[-92.4442,31.3919],[-92.4117,31.3528],[-92.4168,31.3299],[-92.4458,31.3025],[-92.429,31.2487]]}},{"id":"5715","type":"Feature","properties":{"FULLNAME":"US Hwy 167","RTTYP":"U"},"geometry":{"type":"LineString","coordinates":[[-92.053,30.379],[-92.0544,30.4197],[-92.0693,30.4377],[-92.0776,30.4718],[-92.0489,30.5841]]}},{"id":"5716","type":"Feature","properties":{"FULLNAME":"US Hwy 167","RTTYP":"U"},"geometry":{"type":"LineString","coordinates":[[-92.0492,30.5843],[-92.0779,30.4714],[-92.0696,30.4377],[-92.0543,30.4189],[-92.0533,30.379]]}},{"id":"6137","type":"Feature","properties":{"FULLNAME":"I- 10","RTTYP":"I"},"geometry":{"type":"LineString","coordinates":[[-93.7014,30.1273],[-93.7251,30.1186],[-93.7794,30.1212],[-93.8087,30.1129],[-93.864,30.1317],[-93.9685,30.1292],[-94.004,30.1358],[-94.0664,30.0982],[-94.0911,30.0946]]}},{"id":"6147","type":"Feature","properties":{"FULLNAME":"I- 10","RTTYP":"I"},"geometry":{"type":"LineString","coordinates":[[-92.997,30.2502],[-93.1793,30.2468],[-93.1924,30.2362],[-93.2794,30.2369],[-93.3242,30.2161],[-93.4149,30.2145],[-93.5655,30.1854],[-93.7014,30.1273]]}},{"id":"6148","type":"Feature","properties":{"FULLNAME":"I- 10","RTTYP":"I"},"geometry":{"type":"LineString","coordinates":[[-92.997,30.2502],[-92.6495,30.2466],[-92.6225,30.2402]]}},{"id":"6152","type":"Feature","properties":{"FULLNAME":"I- 10","RTTYP":"I"},"geometry":{"type":"LineString","coordinates":[[-93.7014,30.1275],[-93.5645,30.1861],[-93.4117,30.2154],[-93.3244,30.2164],[-93.2805,30.2369],[-93.192,30.2364],[-93.1794,30.2469],[-92.997,30.2507]]}},{"id":"6183","type":"Feature","properties":{"FULLNAME":"I- 10","RTTYP":"I"},"geometry":{"type":"LineString","coordinates":[[-91.95,30.2812],[-92.0486,30.2475],[-92.1762,30.2477]]}},{"id":"6184","type":"Feature","properties":{"FULLNAME":"I- 10","RTTYP":"I"},"geometry":{"type":"LineString","coordinates":[[-92.1762,30.2475],[-92.0486,30.2472],[-91.9499,30.281]]}},{"id":"6250","type":"Feature","properties":{"FULLNAME":"I- 10","RTTYP":"I"},"geometry":{"type":"LineString","coordinates":[[-92.6225,30.2404],[-92.6505,30.2468],[-92.997,30.2507]]}},{"id":"6300","type":"Feature","properties":{"FULLNAME":"I- 10","RTTYP":"I"},"geometry":{"type":"LineString","coordinates":[[-92.1762,30.2477],[-92.2803,30.2523],[-92.34,30.2358],[-92.4863,30.231],[-92.6225,30.2404]]}},{"id":"6310","type":"Feature","properties":{"FULLNAME":"I- 10","RTTYP":"I"},"geometry":{"type":"LineString","coordinates":[[-92.6225,30.2402],[-92.4847,30.2307],[-92.3395,30.2356],[-92.2803,30.2521],[-92.1762,30.2475]]}},{"id":"6794","type":"Feature","properties":{"FULLNAME":"US Hwy 287","RTTYP":"U"},"geometry":{"type":"LineString","coordinates":[[-93.9779,29.9346],[-94.0204,29.9677],[-94.0579,30.0325],[-94.0854,30.0303],[-94.1433,30.0489],[-94.1347,30.0632],[-94.1372,30.108],[-94.1772,30.1434],[-94.1863,30.1792]]}},{"id":"6819","type":"Feature","properties":{"FULLNAME":"US Hwy 287","RTTYP":"U"},"geometry":{"type":"LineString","coordinates":[[-93.9794,29.9358],[-94.0218,29.9698],[-94.0579,30.0327],[-94.085,30.0304],[-94.1407,30.048],[-94.1345,30.0639],[-94.1369,30.1079],[-94.1771,30.1434],[-94.1861,30.1793]]}},{"id":"9031","type":"Feature","properties":{"FULLNAME":"Alexandria Pineville Expy","RTTYP":"M"},"geometry":{"type":"LineString","coordinates":[[-92.4438,31.3052],[-92.4419,31.307]]}},{"id":"9032","type":"Feature","properties":{"FULLNAME":"Alexandria Pineville Expy","RTTYP":"M"},"geometry":{"type":"LineString","coordinates":[[-92.4257,31.3205],[-92.4116,31.3523],[-92.435,31.3806]]}},{"id":"9337","type":"Feature","properties":{"FULLNAME":"I- 10 W","RTTYP":"I"},"geometry":{"type":"LineString","coordinates":[[-93.7014,30.1275],[-93.7246,30.1188],[-93.7794,30.1214],[-93.8086,30.1131],[-93.8633,30.1319],[-93.9691,30.1294],[-94.0045,30.1359],[-94.0663,30.0984],[-94.091,30.0947]]}},{"id":"13372","type":"Feature","properties":{"FULLNAME":"US Hwy 90","RTTYP":"U"},"geometry":{"type":"LineString","coordinates":[[-93.7014,30.1273],[-93.7251,30.1186],[-93.7794,30.1212],[-93.8087,30.1129],[-93.864,30.1317],[-93.9685,30.1292],[-94.004,30.1358],[-94.0664,30.0982],[-94.0911,30.0946]]}},{"id":"13384","type":"Feature","properties":{"FULLNAME":"US Hwy 90","RTTYP":"U"},"geometry":{"type":"LineString","coordinates":[[-93.7014,30.1275],[-93.7246,30.1188],[-93.7794,30.1214],[-93.8086,30.1131],[-93.8633,30.1319],[-93.9691,30.1294],[-94.0045,30.1359],[-94.0663,30.0984],[-94.091,30.0947]]}},{"id":"13391","type":"Feature","properties":{"FULLNAME":"US Hwy 90","RTTYP":"U"},"geometry":{"type":"LineString","coordinates":[[-93.1965,30.2361],[-93.2741,30.2374]]}},{"id":"13393","type":"Feature","properties":{"FULLNAME":"US Hwy 90","RTTYP":"U"},"geometry":{"type":"LineString","coordinates":[[-93.7014,30.1273],[-93.6415,30.153]]}},{"id":"13396","type":"Feature","properties":{"FULLNAME":"US Hwy 90","RTTYP":"U"},"geometry":{"type":"LineString","coordinates":[[-93.1965,30.2362],[-93.2741,30.2376]]}},{"id":"13397","type":"Feature","properties":{"FULLNAME":"US Hwy 90","RTTYP":"U"},"geometry":{"type":"LineString","coordinates":[[-93.6396,30.1541],[-93.7014,30.1275]]}},{"id":"13415","type":"Feature","properties":{"FULLNAME":"I- 49","RTTYP":"I"},"geometry":{"type":"LineString","coordinates":[[-92.7898,31.462],[-92.6762,31.3814],[-92.5056,31.3457],[-92.4922,31.3333],[-92.4606,31.3232],[-92.4287,31.247],[-92.4625,31.2313],[-92.474,31.2006],[-92.4428,31.126],[-92.441,31.0851],[-92.4064,31.0299],[-92.3079,30.9876],[-92.2869,30.9651]]}},{"id":"13416","type":"Feature","properties":{"FULLNAME":"I- 49","RTTYP":"I"},"geometry":{"type":"LineString","coordinates":[[-93.4312,31.9229],[-93.3445,31.8702],[-93.2168,31.8092],[-93.1399,31.7059],[-93.0181,31.5744],[-92.9876,31.5649],[-92.9474,31.5295],[-92.8713,31.501],[-92.8322,31.4742],[-92.7898,31.462]]}},{"id":"13417","type":"Feature","properties":{"FULLNAME":"I- 49","RTTYP":"I"},"geometry":{"type":"LineString","coordinates":[[-93.4312,31.9224],[-93.3455,31.8704],[-93.2171,31.8091],[-93.1382,31.7029],[-93.0185,31.5744],[-92.9882,31.565],[-92.9478,31.5294],[-92.7927,31.462]]}},{"id":"13418","type":"Feature","properties":{"FULLNAME":"I- 49","RTTYP":"I"},"geometry":{"type":"LineString","coordinates":[[-92.2114,30.8023],[-92.1779,30.7685]]}},{"id":"13419","type":"Feature","properties":{"FULLNAME":"I- 49","RTTYP":"I"},"geometry":{"type":"LineString","coordinates":[[-92.1772,30.7684],[-92.2114,30.8028]]}},{"id":"13422","type":"Feature","properties":{"FULLNAME":"I- 49","RTTYP":"I"},"geometry":{"type":"LineString","coordinates":[[-92.1724,30.7643],[-92.0836,30.6954],[-92.0487,30.6393],[-92.0533,30.5491],[-92.0649,30.5347],[-92.0779,30.4714],[-92.0696,30.4377],[-92.0543,30.4189],[-92.0533,30.379]]}},{"id":"13423","type":"Feature","properties":{"FULLNAME":"I- 49","RTTYP":"I"},"geometry":{"type":"LineString","coordinates":[[-92.053,30.379],[-92.0544,30.4197],[-92.0693,30.4377],[-92.0776,30.4718],[-92.0646,30.5349],[-92.053,30.5489],[-92.0486,30.6398],[-92.0838,30.6963],[-92.1724,30.7646]]}},{"id":"13424","type":"Feature","properties":{"FULLNAME":"I- 49","RTTYP":"I"},"geometry":{"type":"LineString","coordinates":[[-92.0155,30.2595],[-92.053,30.379]]}},{"id":"13425","type":"Feature","properties":{"FULLNAME":"I- 49","RTTYP":"I"},"geometry":{"type":"LineString","coordinates":[[-92.0158,30.2594],[-92.0533,30.379]]}},{"id":"13432","type":"Feature","properties":{"FULLNAME":"I- 49","RTTYP":"I"},"geometry":{"type":"LineString","coordinates":[[-92.1779,30.7685],[-92.1724,30.7643]]}},{"id":"13433","type":"Feature","properties":{"FULLNAME":"I- 49","RTTYP":"I"},"geometry":{"type":"LineString","coordinates":[[-92.229,30.8484],[-92.2114,30.8023]]}},{"id":"13434","type":"Feature","properties":{"FULLNAME":"I- 49","RTTYP":"I"},"geometry":{"type":"LineString","coordinates":[[-92.2114,30.8028],[-92.2284,30.8484]]}},{"id":"13436","type":"Feature","properties":{"FULLNAME":"I- 49","RTTYP":"I"},"geometry":{"type":"LineString","coordinates":[[-92.2869,30.9651],[-92.2807,30.9577]]}},{"id":"13440","type":"Feature","properties":{"FULLNAME":"I- 49","RTTYP":"I"},"geometry":{"type":"LineString","coordinates":[[-92.1724,30.7646],[-92.1772,30.7684]]}},{"id":"13441","type":"Feature","properties":{"FULLNAME":"I- 49","RTTYP":"I"},"geometry":{"type":"LineString","coordinates":[[-92.2807,30.9573],[-92.2872,30.9651]]}},{"id":"13442","type":"Feature","properties":{"FULLNAME":"I- 49","RTTYP":"I"},"geometry":{"type":"LineString","coordinates":[[-92.2284,30.8484],[-92.2278,30.8978],[-92.2807,30.9577]]}},{"id":"13452","type":"Feature","properties":{"FULLNAME":"I- 49","RTTYP":"I"},"geometry":{"type":"LineString","coordinates":[[-92.7927,31.462],[-92.6758,31.3809],[-92.5056,31.3454],[-92.4605,31.3228],[-92.429,31.2469],[-92.4627,31.2316],[-92.4743,31.2006],[-92.4428,31.1251],[-92.4435,31.0892],[-92.4082,31.0303],[-92.3071,30.987],[-92.2872,30.9651]]}},{"id":"13453","type":"Feature","properties":{"FULLNAME":"I- 49","RTTYP":"I"},"geometry":{"type":"LineString","coordinates":[[-92.2807,30.9573],[-92.2281,30.8979],[-92.229,30.8484]]}},{"id":"13454","type":"Feature","properties":{"FULLNAME":"I- 49","RTTYP":"I"},"geometry":{"type":"LineString","coordinates":[[-93.7515,32.3398],[-93.7473,32.2679],[-93.7273,32.2356],[-93.616,32.1294],[-93.541,32.0375],[-93.5224,32.0005],[-93.4736,31.9813],[-93.4442,31.9579],[-93.4312,31.9229]]}},{"id":"13467","type":"Feature","properties":{"FULLNAME":"I- 49","RTTYP":"I"},"geometry":{"type":"LineString","coordinates":[[-93.4312,31.9224],[-93.4458,31.9592],[-93.4742,31.9813],[-93.5227,32.0004],[-93.5411,32.0371],[-93.6179,32.1309],[-93.7284,32.2362],[-93.748,32.2682],[-93.7519,32.3398]]}},{"id":"13646","type":"Feature","properties":{"FULLNAME":"US Hwy 69","RTTYP":"U"},"geometry":{"type":"LineString","coordinates":[[-93.9794,29.9358],[-94.0218,29.9698],[-94.0579,30.0327],[-94.085,30.0304],[-94.1407,30.048],[-94.1345,30.0639],[-94.1369,30.1079],[-94.1771,30.1434],[-94.1861,30.1793]]}},{"id":"13672","type":"Feature","properties":{"FULLNAME":"US Hwy 69","RTTYP":"U"},"geometry":{"type":"LineString","coordinates":[[-93.9779,29.9346],[-94.0204,29.9677],[-94.0579,30.0325],[-94.0854,30.0303],[-94.1433,30.0489],[-94.1347,30.0632],[-94.1372,30.108],[-94.1772,30.1434],[-94.1863,30.1792]]}},{"id":"13947","type":"Feature","properties":{"FULLNAME":"I- 210","RTTYP":"I"},"geometry":{"type":"LineString","coordinates":[[-93.1568,30.2453],[-93.1633,30.2418]]}},{"id":"13948","type":"Feature","properties":{"FULLNAME":"I- 210","RTTYP":"I"},"geometry":{"type":"LineString","coordinates":[[-93.1621,30.245],[-93.1633,30.2418]]}},{"id":"13949","type":"Feature","properties":{"FULLNAME":"I- 210","RTTYP":"I"},"geometry":{"type":"LineString","coordinates":[[-93.1671,30.2464],[-93.1621,30.245]]}},{"id":"13950","type":"Feature","properties":{"FULLNAME":"I- 210","RTTYP":"I"},"geometry":{"type":"LineString","coordinates":[[-93.2984,30.2229],[-93.2735,30.1963],[-93.1755,30.1974],[-93.1633,30.2418]]}},{"id":"13951","type":"Feature","properties":{"FULLNAME":"I- 210","RTTYP":"I"},"geometry":{"type":"LineString","coordinates":[[-93.1621,30.245],[-93.1631,30.2435]]}},{"id":"13952","type":"Feature","properties":{"FULLNAME":"I- 210","RTTYP":"I"},"geometry":{"type":"LineString","coordinates":[[-93.1631,30.2435],[-93.1758,30.1976],[-93.2731,30.1963],[-93.2979,30.2228]]}},{"id":"13953","type":"Feature","properties":{"FULLNAME":"I- 210","RTTYP":"I"},"geometry":{"type":"LineString","coordinates":[[-93.1668,30.2461],[-93.1631,30.2435]]}},{"id":"13954","type":"Feature","properties":{"FULLNAME":"I- 210","RTTYP":"I"},"geometry":{"type":"LineString","coordinates":[[-93.156,30.2455],[-93.1621,30.245]]}},{"id":"14266","type":"Feature","properties":{"FULLNAME":"US Hwy 96","RTTYP":"U"},"geometry":{"type":"LineString","coordinates":[[-93.9779,29.9346],[-94.0204,29.9677],[-94.0579,30.0325],[-94.0854,30.0303],[-94.1433,30.0489],[-94.1347,30.0632],[-94.1372,30.108],[-94.1772,30.1434],[-94.1863,30.1792]]}},{"id":"14267","type":"Feature","properties":{"FULLNAME":"US Hwy 96","RTTYP":"U"},"geometry":{"type":"LineString","coordinates":[[-93.9794,29.9358],[-94.0218,29.9698],[-94.0579,30.0327],[-94.085,30.0304],[-94.1407,30.048],[-94.1345,30.0639],[-94.1369,30.1079],[-94.1771,30.1434],[-94.1861,30.1793]]}}],"crs":{"type":"name","properties":{"name":"urn:ogc:def:crs:EPSG::4269"}}}