{"type":"FeatureCollection","features":[{"id":"1699","type":"Feature","properties":{"FULLNAME":"US Hwy 53","RTTYP":"U"},"geometry":{"type":"LineString","coordinates":[[-91.4309,44.8574],[-91.4125,44.8872],[-91.4278,44.9051],[-91.4256,44.961],[-91.4429,44.9866],[-91.4437,45.0221],[-91.4648,45.0471],[-91.4669,45.0671],[-91.5169,45.1102],[-91.5258,45.1684],[-91.5751,45.207]]}},{"id":"1702","type":"Feature","properties":{"FULLNAME":"US Hwy 53","RTTYP":"U"},"geometry":{"type":"LineString","coordinates":[[-91.5745,45.207],[-91.5253,45.1696],[-91.5164,45.11],[-91.4664,45.0672],[-91.4641,45.0467],[-91.4434,45.0225],[-91.4426,44.9868],[-91.4253,44.9617],[-91.4273,44.905],[-91.4121,44.8871],[-91.4305,44.8574]]}},{"id":"1703","type":"Feature","properties":{"FULLNAME":"US Hwy 53","RTTYP":"U"},"geometry":{"type":"LineString","coordinates":[[-91.5745,45.2071],[-91.5926,45.2391],[-91.6495,45.2984],[-91.6771,45.3148],[-91.7086,45.3621],[-91.7543,45.3874],[-91.7634,45.4146],[-91.7604,45.5146]]}},{"id":"1706","type":"Feature","properties":{"FULLNAME":"US Hwy 53","RTTYP":"U"},"geometry":{"type":"LineString","coordinates":[[-91.7613,45.5123],[-91.7642,45.4142],[-91.7546,45.3867],[-91.7087,45.3609],[-91.6777,45.3149],[-91.6494,45.2978],[-91.5935,45.2387],[-91.5752,45.2071]]}},{"id":"1707","type":"Feature","properties":{"FULLNAME":"US Hwy 53","RTTYP":"U"},"geometry":{"type":"LineString","coordinates":[[-91.4209,44.7657],[-91.4562,44.7961],[-91.4534,44.8319],[-91.4309,44.8574]]}},{"id":"1708","type":"Feature","properties":{"FULLNAME":"US Hwy 53","RTTYP":"U"},"geometry":{"type":"LineString","coordinates":[[-91.4198,44.7649],[-91.4559,44.7967],[-91.4525,44.8327],[-91.4305,44.8574]]}},{"id":"5241","type":"Feature","properties":{"FULLNAME":"S Hastings Way","RTTYP":"M"},"geometry":{"type":"LineString","coordinates":[[-91.4479,44.7839],[-91.4401,44.7802]]}},{"id":"5242","type":"Feature","properties":{"FULLNAME":"S Hastings Way","RTTYP":"M"},"geometry":{"type":"LineString","coordinates":[[-91.4595,44.793],[-91.4466,44.7836]]}},{"id":"5243","type":"Feature","properties":{"FULLNAME":"S Hastings Way","RTTYP":"M"},"geometry":{"type":"LineString","coordinates":[[-91.4591,44.7924],[-91.4507,44.7853]]}},{"id":"8517","type":"Feature","properties":{"FULLNAME":"US Hwy 53 Bus","RTTYP":"U"},"geometry":{"type":"LineString","coordinates":[[-91.4595,44.793],[-91.4466,44.7836]]}},{"id":"8518","type":"Feature","properties":{"FULLNAME":"US Hwy 53 Bus","RTTYP":"U"},"geometry":{"type":"LineString","coordinates":[[-91.4591,44.7924],[-91.4507,44.7853]]}},{"id":"15850","type":"Feature","properties":{"FULLNAME":"I- 94","RTTYP":"I"},"geometry":{"type":"LineString","coordinates":[[-91.1657,44.5488],[-91.1164,44.4827],[-91.0466,44.4141],[-90.9521,44.355],[-90.8392,44.308],[-90.8027,44.2772],[-90.5722,44.1602]]}},{"id":"15859","type":"Feature","properties":{"FULLNAME":"I- 94","RTTYP":"I"},"geometry":{"type":"LineString","coordinates":[[-90.5715,44.1601],[-90.5341,44.1328],[-90.5321,44.0935],[-90.5119,44.0278],[-90.4924,44.0154]]}},{"id":"15884","type":"Feature","properties":{"FULLNAME":"I- 94","RTTYP":"I"},"geometry":{"type":"LineString","coordinates":[[-90.4924,44.0154],[-90.4682,43.9963],[-90.3123,43.9432]]}},{"id":"15917","type":"Feature","properties":{"FULLNAME":"I- 94","RTTYP":"I"},"geometry":{"type":"LineString","coordinates":[[-91.6505,44.854],[-91.5815,44.8324],[-91.543,44.7834],[-91.5101,44.7693],[-91.4051,44.7636],[-91.351,44.7191],[-91.3025,44.6382],[-91.2499,44.6181],[-91.2187,44.597]]}},{"id":"15947","type":"Feature","properties":{"FULLNAME":"I- 94","RTTYP":"I"},"geometry":{"type":"LineString","coordinates":[[-91.6505,44.854],[-91.7641,44.9008],[-91.9568,44.9075],[-92.0169,44.9204],[-92.0917,44.9171],[-92.1353,44.9275]]}},{"id":"15948","type":"Feature","properties":{"FULLNAME":"I- 94","RTTYP":"I"},"geometry":{"type":"LineString","coordinates":[[-92.1353,44.9278],[-92.0923,44.9173],[-92.0169,44.9207],[-91.9582,44.9078],[-91.7647,44.9012],[-91.6505,44.8542]]}},{"id":"15949","type":"Feature","properties":{"FULLNAME":"I- 94","RTTYP":"I"},"geometry":{"type":"LineString","coordinates":[[-91.1657,44.5501],[-91.1994,44.5726],[-91.2182,44.597]]}},{"id":"15950","type":"Feature","properties":{"FULLNAME":"I- 94","RTTYP":"I"},"geometry":{"type":"LineString","coordinates":[[-91.2187,44.597],[-91.1986,44.5708],[-91.1657,44.5488]]}},{"id":"15954","type":"Feature","properties":{"FULLNAME":"I- 94","RTTYP":"I"},"geometry":{"type":"LineString","coordinates":[[-90.3123,43.9418],[-90.4462,43.9847],[-90.5096,44.0239],[-90.5324,44.0925],[-90.5343,44.1324],[-90.5722,44.1602]]}},{"id":"15966","type":"Feature","properties":{"FULLNAME":"I- 94","RTTYP":"I"},"geometry":{"type":"LineString","coordinates":[[-90.5715,44.1601],[-90.8028,44.2776],[-90.8387,44.308],[-90.9533,44.356],[-91.0471,44.4149],[-91.116,44.4829],[-91.1657,44.5501]]}},{"id":"15976","type":"Feature","properties":{"FULLNAME":"I- 94","RTTYP":"I"},"geometry":{"type":"LineString","coordinates":[[-91.6505,44.8542],[-91.5805,44.8326],[-91.5423,44.7832],[-91.5098,44.7694],[-91.4051,44.7639],[-91.3508,44.7192],[-91.3023,44.6384],[-91.2499,44.6186],[-91.2182,44.597]]}}],"crs":{"type":"name","properties":{"name":"urn:ogc:def:crs:EPSG::4269"}}}